{
    "TOOLBAR": {
        "BOOKMARK_BUTTON": "#slot-btn-bookmarks"
    },
    "MODAL_WINDOW": {
        "BOOKMARK_WINDOW": "#window-bookmarks",
        "NAME_INPUT": "#bookmarks-txt-name > div",
        "ADD_BUTTON": "#bookmarks-btn-add",
        "CLOSE_BUTTON": "#window-bookmarks > div.body > div.footer.center > button",
        "BOOKMARK_ITEM_BY_NAME": ".listview.inner .list-item",
        "GOTO_BUTTON": "#bookmarks-btn-goto",
        "GET_LINK_BUTTON": "#bookmarks-btn-link",
        "OPENED_GET_LINK_ITEM": "#window-bookmarks tbody td div.open",
        "DELETE_BUTTON": "#bookmarks-btn-delete",
        "LINK_INPUT": ".bookmark-copy-dropdown-input input[readonly]"
    }
}